{
    "id": "OQmWfkPi5sU",
    "title": "Экономика РФ после войны",
    "youtubeLink": "https://www.youtube.com/watch?v=OQmWfkPi5sU",
    "date": "18 июля 2025",
    "sections": [
        {
            "timestamp": "00:02:30",
            "title": "Обзор SPY",
            "tickers": [
                "SPY"
            ],
            "description": "Подробный анализ индекса SPY и его перспектив."
        },
        {
            "timestamp": "00:10:45",
            "title": "Китай и сырьевой рынок",
            "tickers": [
                "FXI",
                "Нефть",
                "Китай"
            ],
            "description": "Влияние китайской экономики на мировые сырьевые рынки."
        },
        {
            "timestamp": "00:18:00",
            "title": "Разбор Tesla",
            "tickers": [
                "TSLA"
            ],
            "description": "Анализ акций Tesla и последние новости компании."
        },
        {
            "timestamp": "00:25:15",
            "title": "Инфляция и процентные ставки",
            "tickers": [
                "Инфляция",
                "Ставки"
            ],
            "description": "Обсуждение текущей инфляции и ожиданий по процентным ставкам."
        }
    ]
}